[
 {
   "id": 1,
   "name": "2021년 서울지식재산센터 IP창업존 IP창업스쿨 2021년 5차(17기) 교육생 모집",
   "day": 11,
   "see": 5883,
   "site": "https://www.sba.seoul.kr/kr/sbcu01s1?bseq=5038090"
 },
 {
   "id": 2,
   "name": "정직한밥상 서포터즈 1기 모집",
   "day": 18,
   "see": 3258,
   "site": "https://htable.co.kr/article/이벤트/3001/18704/"
 },
 {
   "id": 3,
   "name": "2021 대한민국 과일산업대전 우리과일 요리경연대회",
   "day": 22,
   "see": 2680,
   "site": "http://t2m.kr/4LLNp"
 },
 {
   "id": 4,
   "name": "[수원·경기 대외활동] 삼행시(삼성전자와 함께하는 행복한 수원시) 블로그 필진 16기 모집",
   "day": 18,
   "see": 1858,
   "site": "https://www.samsungdigitalcity.com/1924"
 },
 {
   "id": 5,
   "name": "(주)그린패키지솔루션 그린서포터즈 3기 모집",
   "day": 32,
   "see": 1079,
   "site": "https://blog.naver.com/gps-pack/222562151057"
 },
 {
   "id": 6,
   "name": "홈 CCTV 어플 아이봄 베타 테스터 모집",
   "day": 6,
   "see": 200,
   "site": "http://naver.me/GsTnc4aR"
 },
 {
   "id": 7,
   "name": "6주 만에 책 쓰기 프로젝트 [온라인 / 오프라인] 28기 모집",
   "day": 3,
   "see": 323,
   "site": "http://bit.ly/글ego_공식사이트가기_28기"
 },
 {
   "id": 8,
   "name": "2021 미추홀학산문화원 학산동네 서포터즈 '봄이' 모집",
   "day": 1,
   "see": 532,
   "site": "https://www.haksanculture.or.kr/board/view.php?code=notice&sq=1237"
 },
 {
   "id": 9,
   "name": "셰프뮤지엄 서포터즈 2기 모집",
   "day": 4,
   "see": 621,
   "site": "https://forms.gle/AFbKdLQjNkJgSo9k6"
 },
 {
   "id": 10,
   "name": "풀리과외 서포터즈 1기 모집",
   "day": 5,
   "see": 674,
   "site": "https://blog.naver.com/pulley_math/222552515203"
 },
 {
   "id": 11,
   "name": "헤움디자인 1기 서포터즈 모집",
   "day": 9,
   "see": 831,
   "site": "https://www.heumm.com/"
 },
 {
   "id": 12,
   "name": "랭스 서포터즈 랭스인 2기 모집",
   "day": 14,
   "see": 135,
   "site": "https://langscoffeework.com/board/index.php?board=event_01&type=view&select=&search=&idx=23"
 },
 {
   "id": 13,
   "name": "2022년 남양주시 SNS 서포터즈 5기 모집",
   "day": 9,
   "see": 72,
   "site": "https://www.nyj.go.kr/main/185?action-value=04e640b2801e0b28fb4d6fbbcb689773&action=read&space=main_board_gonggo"
 },
 {
   "id": 14,
   "name": "GME 해외송금 서포터즈 1기 모집",
   "day": 51,
   "see": 891,
   "site": "https://www.gmeremit.com/2021/10/22/6671/"
 },
 {
   "id": 15,
   "name": "제4기 성남시 여성친화도시 서포터즈 모집 (기간연장)",
   "day": 20,
   "see": 708,
   "site": "https://www.seongnam.go.kr/city/1000053/30003/bbsView.do?idx=246213"
 },
 {
   "id": 16,
   "name": "2021 레드불 대학생 마케터 모집",
   "day": 51,
   "see": 235,
   "site": "https://forms.gle/P3P5tYkPoNwaX1fa9"
 },
 {
   "id": 17,
   "name": "2021 동백마당 대학생 전문콘텐츠 에디터 모집",
   "day": 51,
   "see": 534,
   "site": "https://blog.naver.com/cs_dongemail/222431078327"
 },
 {
   "id": 18,
   "name": "전라남도 생명사랑 모니터링단 마음클리너 1기 모집",
   "day": 20,
   "see": 342,
   "site": "http://061mind.or.kr/?sid=17&wbb=md:view;uid:450"
 },
 {
   "id": 19,
   "name": "연세테라브레인 서포터즈 모집",
   "day": 51,
   "see": 235,
   "site": "https://www.wevity.com/?c=find&s=1&gbn=view&ix=47607"
 },
 {
   "id": 20,
   "name": "동백마당 동화 서포터즈 상시 모집",
   "day": 33,
   "see": 623,
   "site": "https://dongwhite.com/bbs_detail.php?minihome_id=&bbs_num=3&tb=board_info6&b_category=&"
 }
]